odata/__init__.py
odata/action.py
odata/complextype.py
odata/connection.py
odata/context.py
odata/entity.py
odata/enumtype.py
odata/exceptions.py
odata/metadata.py
odata/navproperty.py
odata/property.py
odata/query.py
odata/service.py
odata/state.py
odata/tests/__init__.py
odata/tests/test_actions.py
odata/tests/test_composite_keys.py
odata/tests/test_context.py
odata/tests/test_enums.py
odata/tests/test_error.py
odata/tests/test_metadata.py
odata/tests/test_navigation.py
odata/tests/test_nw_manual_model.py
odata/tests/test_nw_reflect_model.py
odata/tests/test_objects.py
tctc_odata-0.3.dist-info/METADATA
tctc_odata-0.3.dist-info/RECORD
tctc_odata-0.3.dist-info/WHEEL
tctc_odata-0.3.dist-info/top_level.txt
